LICENSE.rst
MANIFEST.in
README.rst
setup.cfg
setup.py
predicates/__init__.py
predicates.egg-info/PKG-INFO
predicates.egg-info/SOURCES.txt
predicates.egg-info/dependency_links.txt
predicates.egg-info/namespace_packages.txt
predicates.egg-info/requires.txt
predicates.egg-info/top_level.txt