Metadata-Version: 1.1
Name: predicates
Version: 0.0.5
Summary: A collection of predicate factories, functions, and partials, for functional programming.
Home-page: https://github.com/agoraplex/predicates
Author: Tripp Lilley
Author-email: tripplilley@gmail.com
License: BSD
Platform: UNKNOWN
Classifier: Development Status :: 3 - Alpha
Classifier: Intended Audience :: Developers
Classifier: Operating System :: OS Independent
Classifier: Programming Language :: Python :: 2.7
Classifier: Topic :: Software Development :: Libraries :: Python Modules
